MANIFEST.in
requirements.txt
setup.py
minium/__init__.py
minium.egg-info/PKG-INFO
minium.egg-info/SOURCES.txt
minium.egg-info/dependency_links.txt
minium.egg-info/entry_points.txt
minium.egg-info/requires.txt
minium.egg-info/top_level.txt
minium/externlib/__init__.py
minium/externlib/requirements.txt
minium/externlib/android_base/__init__.py
minium/externlib/at/__init__.py
minium/externlib/at/apkapi.py
minium/externlib/at/atproxy.py
minium/externlib/at/command_line.py
minium/externlib/at/eventmonitor.py
minium/externlib/at/hook.py
minium/externlib/at/jlogcat.py
minium/externlib/at/keycode.py
minium/externlib/at/perfcollector.py
minium/externlib/at/requirements.txt
minium/externlib/at/wsimp.py
minium/externlib/at/bin/AtServer.apk
minium/externlib/at/bin/AtStub.jar
minium/externlib/at/core/__init__.py
minium/externlib/at/core/accesshelper.py
minium/externlib/at/core/adbwrap.py
minium/externlib/at/core/basedriver.py
minium/externlib/at/core/case_repair_adapter.py
minium/externlib/at/core/config.py
minium/externlib/at/core/element.py
minium/externlib/at/core/exceptions.py
minium/externlib/at/core/javadriver.py
minium/externlib/at/core/resguard.py
minium/externlib/at/core/uidevice.py
minium/externlib/at/core/uixml.py
minium/externlib/at/core/websocketcli.py
minium/externlib/at/core/stf/__init__.py
minium/externlib/at/core/stf/mincap.py
minium/externlib/at/core/stf/minitouch.py
minium/externlib/at/tests/AtEvent.py
minium/externlib/at/tests/AtSocket.py
minium/externlib/at/tests/__init__.py
minium/externlib/at/tests/adbtest.py
minium/externlib/at/tests/airtesttest.py
minium/externlib/at/tests/atdevicetest.py
minium/externlib/at/tests/attestbase.py
minium/externlib/at/tests/drivertest.py
minium/externlib/at/tests/elementtest.py
minium/externlib/at/tests/javadrivertest.py
minium/externlib/at/tests/minicap_test.py
minium/externlib/at/tests/minitest.py
minium/externlib/at/tests/minitouch_test.py
minium/externlib/at/tests/u2test.py
minium/externlib/at/tests/uixmltest.py
minium/externlib/at/tests/vs_test.py
minium/externlib/at/tests/webdrivertest.py
minium/externlib/at/tests/images/1.jpg
minium/externlib/at/tests/images/2.jpg
