Metadata-Version: 2.1
Name: minium
Version: 1.6.0
Summary: Minium is the best MiniProgram auto test framework.
Home-page: https://minitest.weixin.qq.com/#/
Author: WeChat-Test
Author-email: minitest@tencent.com
License: MIT
Keywords: minium,WeApp,MiniProgram,Automation,Test
Platform: MacOS
Platform: Windows
Requires-Python: >=3.8
Provides-Extra: ios
